dftest/DFTests.py
dftest/Test.py
dftest/__init__.py
dftest/options.py
dftest/style.py
dftest/tests.py
dftest/utils.py
dftest-0.4.0.data/scripts/dftest
frametests/DBTests.py
frametests/Test.py
frametests/__init__.py
frametests/style.py
frametests/tests.py
frametests/utils.py
dftest-0.4.0.dist-info/METADATA
dftest-0.4.0.dist-info/WHEEL
dftest-0.4.0.dist-info/top_level.txt
dftest-0.4.0.dist-info/RECORD
